setup.py
mana/__init__.py
mana/mana.py
mana/templates.py
mana0.egg-info/PKG-INFO
mana0.egg-info/SOURCES.txt
mana0.egg-info/dependency_links.txt
mana0.egg-info/entry_points.txt
mana0.egg-info/not-zip-safe
mana0.egg-info/requires.txt
mana0.egg-info/top_level.txt